{"category": "educational,entertainment,software", "lang": "fr", "age_range": "children,young adult,adult", "rating": "0.0", "description": "Java physics simulations in French (or maybe they're really in English? I can't run them so I don't actually know). Includes Java for Windows.", "intended_use": "html", "prereq_note": "", "zip_http_url": null, "title": "PhET Physics - Haiti", "index_mod_sample_url": "http://dev.worldpossible.org/cgi/sample_wrap.php?moddir=fr-phet-haiti", "zip_ftp_url": null, "prereq_id": null, "source_url": "http://haiti.mit.edu/files/january-2013-workshop/fizik-physics/phet.html", "file_count": "166", "ksize": "133272", "menu_item_name": "fr-phet-haiti", "module_id": "84", "is_hidden": false, "logo_url": "fr-phet-haiti.png", "rsync_url": "rsync://dev.worldpossible.org/rachelmods/fr-phet-haiti", "moddir": "fr-phet-haiti"}